devo/__init__.py
devo/config.py
devo/create/__init__.py
devo/create/commands.py
devo/create/utils.py
devo/exceptions.py
devo/generate/__init__.py
devo/generate/commands.py
devo/generate/utils.py
devo/gitlab/__init__.py
devo/gitlab/commands.py
devo/gitlab/utils.py
devo/kube/__init__.py
devo/kube/commands.py
devo/kube/utils.py
devo/main.py
devo/templates/ci/.gitlab-ci.yml
devo/templates/k8s/base/app/deployment.yaml
devo/templates/k8s/base/app/kustomization.yaml
devo/templates/k8s/base/app/service.yaml
devo/templates/k8s/base/db/deployment.yaml
devo/templates/k8s/base/db/kustomization.yaml
devo/templates/k8s/base/db/service.yaml
devo/templates/k8s/base/kustomization.yaml
devo/templates/k8s/prod/kustomization.yaml
devo/templates/k8s/prod/prod.env
devo/templates/k8s/stage/ingress.yaml
devo/templates/k8s/stage/kustomization.yaml
devo/templates/k8s/test/kustomization.yaml
devo/templates/project/.devo/credentials.env
devo/templates/project/.devo/gitlab.yaml
devo/templates/project/.dockerignore
devo/templates/project/.editorconfig
devo/templates/project/.gitignore
devo/templates/project/Dockerfile
devo/templates/project/README.md
devo/templates/project/devo.yaml
devo/templates/project/requirements/base.txt
devo/templates/project/requirements/prod.txt
devo/templates/project/requirements/test.txt
devo/templates/project/scripts/dev
devo/templates/project/scripts/lint
devo/templates/project/scripts/migrate
devo/templates/project/scripts/prod
devo/templates/project/scripts/test
devo/templates/project/setup.cfg
devo/templates/project/src/main.py
devo/templates/project/tests/test_main.py
devo/templates/skaffold/skaffold.yaml
devo/utils.py
devo-0.9.0.dist-info/entry_points.txt
devo-0.9.0.dist-info/LICENSE
devo-0.9.0.dist-info/WHEEL
devo-0.9.0.dist-info/METADATA
devo-0.9.0.dist-info/RECORD
