Metadata-Version: 2.1
Name: devo
Version: 0.9.0
Summary: 
License: MIT
Author: Dominic Werner
Author-email: aka.vince@gmail.com
Requires-Python: >=3.6,<4.0
Classifier: License :: OSI Approved :: MIT License
Classifier: Programming Language :: Python :: 3
Classifier: Programming Language :: Python :: 3.6
Classifier: Programming Language :: Python :: 3.7
Requires-Dist: click (>=7.0,<8.0)
Requires-Dist: jinja2 (>=2.10,<3.0)
Requires-Dist: python-gitlab (>=1.8,<2.0)
Requires-Dist: ruamel.yaml (>=0.15.94,<0.16.0)
